my_own_package/__init__.py
Oliviu_project_hello-0.2.0.dist-info/METADATA
Oliviu_project_hello-0.2.0.dist-info/WHEEL
Oliviu_project_hello-0.2.0.dist-info/top_level.txt
Oliviu_project_hello-0.2.0.dist-info/RECORD
