Metadata-Version: 2.1
Name: Oliviu-project-hello
Version: 0.2.0
Summary: Hello
Author: Oliviu P.
Author-email: popa.oliviu93@gmail.com
License: UNKNOWN
Platform: UNKNOWN
